MANIFEST.in
readme.rst
setup.py
django_quieter_formset.egg-info/PKG-INFO
django_quieter_formset.egg-info/SOURCES.txt
django_quieter_formset.egg-info/dependency_links.txt
django_quieter_formset.egg-info/top_level.txt
django_quieter_formset.egg-info/zip-safe
quieter_formset/__init__.py
quieter_formset/formset.py
quieter_formset/tests.py