Metadata-Version: 1.1
Name: django-quieter-formset
Version: 0.4
Summary: Django formset that's a bit quieter
Home-page: http://mozilla.com
Author: Mozilla
Author-email: andym@mozilla.com
License: BSD
Platform: UNKNOWN
Classifier: Programming Language :: Python
Classifier: Topic :: Software Development :: Libraries :: Python Modules
Classifier: Environment :: Web Environment :: Mozilla
Classifier: Framework :: Django
